{
	"cmake" : 
	{
		"generator" : 
		{
			"multiConfig" : false,
			"name" : "Ninja"
		},
		"paths" : 
		{
			"cmake" : "C:/Users/yusuf/AppData/Local/JetBrains/Toolbox/apps/CLion/ch-0/231.9011.31/bin/cmake/win/x64/bin/cmake.exe",
			"cpack" : "C:/Users/yusuf/AppData/Local/JetBrains/Toolbox/apps/CLion/ch-0/231.9011.31/bin/cmake/win/x64/bin/cpack.exe",
			"ctest" : "C:/Users/yusuf/AppData/Local/JetBrains/Toolbox/apps/CLion/ch-0/231.9011.31/bin/cmake/win/x64/bin/ctest.exe",
			"root" : "C:/Users/yusuf/AppData/Local/JetBrains/Toolbox/apps/CLion/ch-0/231.9011.31/bin/cmake/win/x64/share/cmake-3.25"
		},
		"version" : 
		{
			"isDirty" : false,
			"major" : 3,
			"minor" : 25,
			"patch" : 2,
			"string" : "3.25.2",
			"suffix" : ""
		}
	},
	"objects" : 
	[
		{
			"jsonFile" : "codemodel-v2-7c0dcf6dc97240fad757.json",
			"kind" : "codemodel",
			"version" : 
			{
				"major" : 2,
				"minor" : 4
			}
		},
		{
			"jsonFile" : "cache-v2-d8459ffb4abb2e0e523d.json",
			"kind" : "cache",
			"version" : 
			{
				"major" : 2,
				"minor" : 0
			}
		},
		{
			"jsonFile" : "cmakeFiles-v1-a6797dd2c5d7db7f6933.json",
			"kind" : "cmakeFiles",
			"version" : 
			{
				"major" : 1,
				"minor" : 0
			}
		},
		{
			"jsonFile" : "toolchains-v1-2b8b580cd147505b2406.json",
			"kind" : "toolchains",
			"version" : 
			{
				"major" : 1,
				"minor" : 0
			}
		}
	],
	"reply" : 
	{
		"cache-v2" : 
		{
			"jsonFile" : "cache-v2-d8459ffb4abb2e0e523d.json",
			"kind" : "cache",
			"version" : 
			{
				"major" : 2,
				"minor" : 0
			}
		},
		"cmakeFiles-v1" : 
		{
			"jsonFile" : "cmakeFiles-v1-a6797dd2c5d7db7f6933.json",
			"kind" : "cmakeFiles",
			"version" : 
			{
				"major" : 1,
				"minor" : 0
			}
		},
		"codemodel-v2" : 
		{
			"jsonFile" : "codemodel-v2-7c0dcf6dc97240fad757.json",
			"kind" : "codemodel",
			"version" : 
			{
				"major" : 2,
				"minor" : 4
			}
		},
		"toolchains-v1" : 
		{
			"jsonFile" : "toolchains-v1-2b8b580cd147505b2406.json",
			"kind" : "toolchains",
			"version" : 
			{
				"major" : 1,
				"minor" : 0
			}
		}
	}
}
